medvae/__init__.py
medvae/medvae_cls.py
medvae/medvae_finetune.py
medvae/medvae_finetune_s2.py
medvae/medvae_inference.py
medvae/medvae_main.py
medvae/models/__init__.py
medvae/models/autoencoder_kl.py
medvae/models/autoencoder_kl_3d.py
medvae/utils/__init__.py
medvae/utils/extras.py
medvae/utils/factory.py
medvae/utils/loaders.py
medvae/utils/lora.py
medvae/utils/lr_schedulers.py
medvae/utils/transforms.py
medvae/utils/vae/__init__.py
medvae/utils/vae/diffusionmodels.py
medvae/utils/vae/diffusionmodels_3d.py
medvae/utils/vae/distributions.py
medvae/utils/vae/loss_components.py
medvae/utils/vae/train_components.py
medvae/utils/vae/train_components_stage2.py
medvae-0.1.7.dist-info/licenses/LICENSE
medvae-0.1.7.dist-info/METADATA
medvae-0.1.7.dist-info/WHEEL
medvae-0.1.7.dist-info/entry_points.txt
medvae-0.1.7.dist-info/top_level.txt
medvae-0.1.7.dist-info/RECORD
