Metadata-Version: 2.4
Name: medvae
Version: 0.1.7
Summary: MedVAE is a family of six medical image autoencoders that can encode high-dimensional medical images into latent representations.
Author: Stanford Machine Intelligence for Medical Imaging (MIMI)
Author-email: Maya Varma <mayavarma@cs.stanford.edu>, Ashwin Kumar <akkumar@stanford.edu>, Rogier van der Sluijs <sluijs@stanford.edu>
License: MIT License
Project-URL: homepage, https://github.com/StanfordMIMI/MedVAE
Project-URL: repository, https://github.com/StanfordMIMI/MedVAE
Keywords: deep learning,image compression,compression,efficiency,computer aided diagnosis,medical image analysis,autoencoders,representation learning,Med-VAE,medvae
Classifier: Development Status :: 5 - Production/Stable
Classifier: Intended Audience :: Developers
Classifier: Intended Audience :: Science/Research
Classifier: Intended Audience :: Healthcare Industry
Classifier: Programming Language :: Python :: 3
Classifier: License :: OSI Approved :: MIT License
Classifier: Topic :: Scientific/Engineering :: Artificial Intelligence
Classifier: Topic :: Scientific/Engineering :: Medical Science Apps.
Requires-Python: >=3.9
License-File: LICENSE
Requires-Dist: torch>=2.4.1
Requires-Dist: accelerate>=0.34.2
Requires-Dist: wandb==0.14.0; python_version < "3.12"
Requires-Dist: wandb>=0.16.0; python_version >= "3.12"
Requires-Dist: tqdm
Requires-Dist: dicom2nifti
Requires-Dist: scipy
Requires-Dist: batchgenerators>=0.25
Requires-Dist: numpy>=1.24
Requires-Dist: scikit-learn
Requires-Dist: scikit-image>=0.19.3
Requires-Dist: SimpleITK>=2.4.0
Requires-Dist: omegaconf>=2.3.0
Requires-Dist: pandas
Requires-Dist: requests
Requires-Dist: nibabel
Requires-Dist: matplotlib
Requires-Dist: seaborn
Requires-Dist: imagecodecs
Requires-Dist: yacs
Requires-Dist: batchgeneratorsv2>=0.2
Requires-Dist: einops>=0.8.0
Requires-Dist: monai>=1.3.2
Requires-Dist: torchvision>=0.19.1
Requires-Dist: gdown
Requires-Dist: nilearn
Requires-Dist: pyrootutils
Requires-Dist: hydra-core
Requires-Dist: torchmetrics
Requires-Dist: hydra-colorlog
Requires-Dist: open_clip_torch==2.24.0
Requires-Dist: polars>=0.19.10
Requires-Dist: rich
Provides-Extra: dev
Requires-Dist: ruff; extra == "dev"
Requires-Dist: pre-commit; extra == "dev"
Requires-Dist: mdformat; extra == "dev"
Dynamic: license-file
